soos-container/__init__.py
soos-container/cli.py
soos_container/__init__.py
soos_container/cli.py
soos_container-0.5.dist-info/METADATA
soos_container-0.5.dist-info/WHEEL
soos_container-0.5.dist-info/entry_points.txt
soos_container-0.5.dist-info/top_level.txt
soos_container-0.5.dist-info/RECORD
